ms_salesforce_to_bigquery/__init__.py
ms_salesforce_to_bigquery/salesforce/Auth.py
ms_salesforce_to_bigquery/salesforce/JWTGenerator.py
ms_salesforce_to_bigquery/salesforce/SalesforceQueryExecutor.py
ms_salesforce_to_bigquery/salesforce/__init__.py
ms_salesforce_to_bigquery/salesforce/__tests__/__init__.py
ms_salesforce_to_bigquery/salesforce/__tests__/test_Auth.py
ms_salesforce_to_bigquery/salesforce/__tests__/test_JWTGenerator.py
ms_salesforce_to_bigquery/salesforce/__tests__/test_SalesforceRequester.py
ms_salesforce_to_bigquery/salesforce/project/__init__.py
ms_salesforce_to_bigquery/salesforce/project/__tests__/__init__.py
ms_salesforce_to_bigquery/salesforce/project/__tests__/test_Project.py
ms_salesforce_to_bigquery/salesforce/project/dto/__init__.py
ms_salesforce_to_bigquery-0.0.9.dist-info/LICENSE
ms_salesforce_to_bigquery-0.0.9.dist-info/METADATA
ms_salesforce_to_bigquery-0.0.9.dist-info/WHEEL
ms_salesforce_to_bigquery-0.0.9.dist-info/RECORD
