Metadata-Version: 2.1
Name: ms-salesforce-to-bigquery
Version: 0.0.9
Summary: Python library used to extract data from Salesforce API and migrate it to Bigquery.
Author: Making Science
Requires-Python: >=3.8.1,<4.0.0
Classifier: Programming Language :: Python :: 3
Classifier: Programming Language :: Python :: 3.9
Classifier: Programming Language :: Python :: 3.10
Classifier: Programming Language :: Python :: 3.11
Requires-Dist: flake8 (>=6.0.0,<7.0.0)
Requires-Dist: isort (>=5.12.0,<6.0.0)
Requires-Dist: pre-commit (>=3.1.1,<4.0.0)
Requires-Dist: pyjwt[crypto] (>=2.6.0,<3.0.0)
Requires-Dist: requests (>=2.28.2,<3.0.0)
